swiftmess.py
swiftmess-0.2.dist-info/LICENSE
swiftmess-0.2.dist-info/METADATA
swiftmess-0.2.dist-info/WHEEL
swiftmess-0.2.dist-info/top_level.txt
swiftmess-0.2.dist-info/RECORD
