Metadata-Version: 2.1
Name: swiftmess
Version: 0.2
Summary: parse SWIFT messages for financial transactions
Home-page: http://pypi.python.org/pypi/swiftmess/
Author: Thomas Aglassinger
Author-email: roskakori@users.sourceforge.net
License: UNKNOWN
Keywords: swift bank banking financial message
Platform: UNKNOWN
Classifier: Development Status :: 4 - Beta
Classifier: Environment :: Console
Classifier: Intended Audience :: Developers
Classifier: Intended Audience :: Financial and Insurance Industry
Classifier: License :: OSI Approved :: GNU Library or Lesser General Public License (LGPL)
Classifier: Natural Language :: English
Classifier: Operating System :: OS Independent
Classifier: Programming Language :: Python :: 2.5
Classifier: Programming Language :: Python :: 2.6
Classifier: Programming Language :: Python :: 2.7
Classifier: Topic :: Office/Business :: Financial
Classifier: Topic :: Text Processing
Requires-Dist: setuptools
